foeworkers/__init__.py
foeworkers-1.0.4.dist-info/DESCRIPTION.rst
foeworkers-1.0.4.dist-info/METADATA
foeworkers-1.0.4.dist-info/RECORD
foeworkers-1.0.4.dist-info/WHEEL
foeworkers-1.0.4.dist-info/entry_points.txt
foeworkers-1.0.4.dist-info/metadata.json
foeworkers-1.0.4.dist-info/top_level.txt
