Metadata-Version: 2.0
Name: foeworkers
Version: 1.0.4
Summary: FareOn eshop workers
Home-page: UNKNOWN
Author: Vojtěch Pachol
Author-email: v.pachol@mikroelektronika.cz
License: UNKNOWN
Keywords: python,eshop,fareon
Platform: UNKNOWN
Classifier: Development Status :: 4 - Beta
Classifier: Programming Language :: Python :: 3
Requires-Dist: PyYAML
Requires-Dist: motor (<2)
Requires-Dist: tornado (<5)
Requires-Dist: zeep
